importmap/__init__.py
importmap/apps.py
importmap/core.py
importmap/generator.py
importmap/management/commands/importmap_generate.py
importmap/models.py
importmap/templates/importmap/scripts.html
importmap/templatetags/__init__.py
importmap/templatetags/importmap.py
django_importmap-0.3.0.dist-info/LICENSE
django_importmap-0.3.0.dist-info/METADATA
django_importmap-0.3.0.dist-info/WHEEL
django_importmap-0.3.0.dist-info/RECORD
