Metadata-Version: 2.1
Name: django-importmap
Version: 0.3.0
Summary: JavaScript import maps for Django
Home-page: https://github.com/dropseed/django-importmap
License: MIT
Keywords: django,javascript,import,map,import-maps
Author: Dave Gaeddert
Author-email: dave.gaeddert@dropseed.dev
Requires-Python: >=3.8,<4.0
Classifier: Environment :: Web Environment
Classifier: Framework :: Django
Classifier: Intended Audience :: Developers
Classifier: License :: OSI Approved :: MIT License
Classifier: Operating System :: OS Independent
Classifier: Programming Language :: Python
Classifier: Programming Language :: Python :: 3
Classifier: Programming Language :: Python :: 3.8
Classifier: Programming Language :: Python :: 3.9
Classifier: Programming Language :: Python :: 3.10
Classifier: Programming Language :: Python :: 3.11
Classifier: Programming Language :: Python :: 3.12
Classifier: Programming Language :: Python :: 3 :: Only
Requires-Dist: requests
Requires-Dist: tomli ; python_version < "3.12"
Project-URL: Documentation, https://github.com/dropseed/django-importmap
Project-URL: Repository, https://github.com/dropseed/django-importmap
